HISTORY.md
microquake/__init__.py
microquake/clients/__init__.py
microquake/clients/api_client.py
microquake/clients/ims/__init__.py
microquake/clients/ims/web_client.py
microquake/core/__init__.py
microquake/core/ctl.py
microquake/core/data/__init__.py
microquake/core/data/grid.py
microquake/core/data/inventory.py
microquake/core/data/resources/L-22D.response
microquake/core/data/response_utils.py
microquake/core/data/station.py
microquake/core/data/ttable.py
microquake/core/data/write_ot.py
microquake/core/decorators.py
microquake/core/event.py
microquake/core/focal_mechanism.py
microquake/core/helpers/__init__.py
microquake/core/helpers/grid.py
microquake/core/helpers/hdf5.py
microquake/core/helpers/nlloc.py
microquake/core/helpers/prepare.py
microquake/core/helpers/time.py
microquake/core/helpers/timescale_db.py
microquake/core/helpers/velocity.py
microquake/core/nlloc.py
microquake/core/settings.py
microquake/core/settings.toml
microquake/core/simul/__init__.py
microquake/core/simul/eik.py
microquake/core/stream.py
microquake/core/trace.py
microquake/core/util/__init__.py
microquake/core/util/base.py
microquake/core/util/borehole.py
microquake/core/util/cepstrum.py
microquake/core/util/cli.py
microquake/core/util/decorator.py
microquake/core/util/serializer.py
microquake/core/util/tools.py
microquake/db/__init__.py
microquake/db/connectors.py
microquake/db/models/__init__.py
microquake/db/models/alchemy.py
microquake/db/models/redis.py
microquake/db/serializers/__init__.py
microquake/imaging/plot.py
microquake/imaging/stereonet.py
microquake/imaging/waveform.py
microquake/io/inventory/__init__.py
microquake/io/inventory/core.py
microquake/io/json/__init__.py
microquake/io/json/core.py
microquake/io/msgpack/__init__.py
microquake/io/msgpack/core.py
microquake/io/waveform/__init__.py
microquake/io/waveform/core.py
microquake/ml/__init__.py
microquake/ml/classifier.py
microquake/ml/signal_noise_classifier.py
microquake/pipelines/__init__.py
microquake-0.2.1.dist-info/entry_points.txt
microquake-0.2.1.dist-info/WHEEL
microquake-0.2.1.dist-info/METADATA
microquake-0.2.1.dist-info/RECORD
